tsqueue/__init__.py
tsqueue/async_queue.py
tsqueue/persistent_queue.py
tsqueue/priority_queue.py
tsqueue/queue.py
tsqueue-0.3.0.dist-info/licenses/LICENSE
tsqueue-0.3.0.dist-info/METADATA
tsqueue-0.3.0.dist-info/WHEEL
tsqueue-0.3.0.dist-info/top_level.txt
tsqueue-0.3.0.dist-info/RECORD
