Metadata-Version: 2.4
Name: tsqueue
Version: 0.3.0
Summary: Thread-safe queue ultra simple pour Python
Author: Nytrox
License: MIT
Project-URL: Homepage, https://github.com/Nytrox-d3v/tsqueue
Keywords: thread-safe,queue,python,tsqueue
Classifier: Programming Language :: Python :: 3
Classifier: License :: OSI Approved :: MIT License
Classifier: Operating System :: OS Independent
Requires-Python: >=3.9
License-File: LICENSE
Dynamic: license-file
